COPYING
COPYING.LESSER
MANIFEST.in
README.txt
pyproject.toml
setup.py
doc/index.php
doc/html/.buildinfo
doc/html/aop.html
doc/html/api-aop.html
doc/html/api-core.html
doc/html/api-ldap.html
doc/html/api-misc.html
doc/html/api-orm.html
doc/html/api-pc.html
doc/html/api.html
doc/html/basic-concepts.html
doc/html/ex1.html
doc/html/ex2.html
doc/html/example-appcontext.html
doc/html/example-tmplproject.html
doc/html/examples.html
doc/html/genindex.html
doc/html/index.html
doc/html/objects.inv
doc/html/py-modindex.html
doc/html/readme.html
doc/html/search.html
doc/html/searchindex.js
doc/html/_modules/builtins.html
doc/html/_modules/index.html
doc/html/_modules/summer/aop.html
doc/html/_modules/summer/ass.html
doc/html/_modules/summer/context.html
doc/html/_modules/summer/dao.html
doc/html/_modules/summer/domain.html
doc/html/_modules/summer/ex.html
doc/html/_modules/summer/ipythonutils.html
doc/html/_modules/summer/l10n.html
doc/html/_modules/summer/ldapdao.html
doc/html/_modules/summer/lod.html
doc/html/_modules/summer/lsf.html
doc/html/_modules/summer/lx.html
doc/html/_modules/summer/lxaop.html
doc/html/_modules/summer/pc.html
doc/html/_modules/summer/pcg.html
doc/html/_modules/summer/sf.html
doc/html/_modules/summer/stringutils.html
doc/html/_modules/summer/tx.html
doc/html/_modules/summer/txaop.html
doc/html/_modules/summer/utils.html
doc/html/_modules/summer/tests/examples/appcontext/appcontext.html
doc/html/_modules/summer/tests/examples/tmplproject/tmplprojecttest.html
doc/html/_sources/aop.txt
doc/html/_sources/api-aop.rst.txt
doc/html/_sources/api-aop.txt
doc/html/_sources/api-core.rst.txt
doc/html/_sources/api-core.txt
doc/html/_sources/api-ldap.rst.txt
doc/html/_sources/api-ldap.txt
doc/html/_sources/api-misc.rst.txt
doc/html/_sources/api-misc.txt
doc/html/_sources/api-orm.rst.txt
doc/html/_sources/api-orm.txt
doc/html/_sources/api-pc.rst.txt
doc/html/_sources/api-pc.txt
doc/html/_sources/api.rst.txt
doc/html/_sources/api.txt
src/summer.egg-info/PKG-INFO
src/summer.egg-info/SOURCES.txt
src/summer.egg-info/dependency_links.txt
src/summer.egg-info/requires.txt
src/summer.egg-info/top_level.txt
